miyadaiku/__init__.py
miyadaiku/builder.py
miyadaiku/config.py
miyadaiku/contents.py
miyadaiku/context.py
miyadaiku/depends.py
miyadaiku/exceptions.py
miyadaiku/extend.py
miyadaiku/html.py
miyadaiku/ipynb.py
miyadaiku/jinjaenv.py
miyadaiku/loader.py
miyadaiku/md.py
miyadaiku/mp_log.py
miyadaiku/parsesrc.py
miyadaiku/pygment_directive.py
miyadaiku/rst.py
miyadaiku/setuputils.py
miyadaiku/site.py
miyadaiku/sitemap.py
miyadaiku/text.py
miyadaiku/scripts/__init__.py
miyadaiku/scripts/muneage.py
miyadaiku/scripts/observer.py
miyadaiku/scripts/zichinsai.py
miyadaiku/themes/__init__.py
miyadaiku/themes/base/__init__.py
miyadaiku/themes/base/config.yml
miyadaiku/themes/base/templates/base.html
miyadaiku/themes/base/templates/jinja_text.txt
miyadaiku/themes/base/templates/macros.html
miyadaiku/themes/base/templates/page_article.html
miyadaiku/themes/base/templates/page_index.html
miyadaiku/themes/base/templates/plain.txt
miyadaiku/themes/docutils_html5/__init__.py
miyadaiku/themes/docutils_html5/templates/macros.html
miyadaiku/themes/ipynb/__init__.py
miyadaiku/themes/ipynb/empty.ipynb
miyadaiku/themes/ipynb/files/static/ipynb/styles/min_ipynb.css
miyadaiku/themes/ipynb/templates/macros.html
miyadaiku/themes/pygments/__init__.py
miyadaiku/themes/pygments/config.yml
miyadaiku/themes/pygments/externals/pygments_abap.css
miyadaiku/themes/pygments/externals/pygments_algol.css
miyadaiku/themes/pygments/externals/pygments_algol_nu.css
miyadaiku/themes/pygments/externals/pygments_arduino.css
miyadaiku/themes/pygments/externals/pygments_autumn.css
miyadaiku/themes/pygments/externals/pygments_borland.css
miyadaiku/themes/pygments/externals/pygments_bw.css
miyadaiku/themes/pygments/externals/pygments_colorful.css
miyadaiku/themes/pygments/externals/pygments_default.css
miyadaiku/themes/pygments/externals/pygments_emacs.css
miyadaiku/themes/pygments/externals/pygments_friendly.css
miyadaiku/themes/pygments/externals/pygments_fruity.css
miyadaiku-1.27.0.dist-info/METADATA
miyadaiku-1.27.0.dist-info/WHEEL
miyadaiku-1.27.0.dist-info/entry_points.txt
miyadaiku-1.27.0.dist-info/top_level.txt
miyadaiku-1.27.0.dist-info/RECORD
