Metadata-Version: 2.4
Name: miyadaiku
Version: 1.27.0
Summary: Miyadaiku - Flexible static site generator for Jinja2 artists
Home-page: https://miyadaiku.github.io
Author: Atsuo Ishimoto
License: MIT
Project-URL: Documentation, https://miyadaiku.github.io/
Project-URL: Source, https://github.com/miyadaiku/miyadaiku
Classifier: Programming Language :: Python :: 3
Classifier: Programming Language :: Python :: 3.13
Classifier: Development Status :: 5 - Production/Stable
Classifier: Environment :: Console
Classifier: Environment :: Web Environment
Classifier: Intended Audience :: Developers
Classifier: Operating System :: OS Independent
Classifier: License :: OSI Approved :: MIT License
Requires-Python: >=3.12
Requires-Dist: tzlocal
Requires-Dist: docutils
Requires-Dist: pyyaml
Requires-Dist: jinja2
Requires-Dist: python-dateutil
Requires-Dist: pygments
Requires-Dist: pytz
Requires-Dist: tzlocal
Requires-Dist: beautifulsoup4
Requires-Dist: feedgenerator
Requires-Dist: markdown>=3.0
Requires-Dist: nbformat
Requires-Dist: nbconvert>=6.0.6
Requires-Dist: watchdog
Requires-Dist: ipython
Requires-Dist: importlib_resources
Provides-Extra: dev
Requires-Dist: wheel; extra == "dev"
Requires-Dist: twine; extra == "dev"
Requires-Dist: pytest; extra == "dev"
Requires-Dist: mypy; extra == "dev"
Requires-Dist: black; extra == "dev"
Requires-Dist: flake8; extra == "dev"
Requires-Dist: autoflake; extra == "dev"
Requires-Dist: pre-commit; extra == "dev"
